tests/__init__.py
tests/test_stack.py
pangolin_tool-0.0.1.dist-info/LICENSE
pangolin_tool-0.0.1.dist-info/METADATA
pangolin_tool-0.0.1.dist-info/WHEEL
pangolin_tool-0.0.1.dist-info/top_level.txt
pangolin_tool-0.0.1.dist-info/RECORD
